lm_mcp/__init__.py
lm_mcp/config.py
lm_mcp/exceptions.py
lm_mcp/health.py
lm_mcp/logging.py
lm_mcp/py.typed
lm_mcp/registry.py
lm_mcp/server.py
lm_mcp/session.py
lm_mcp/validation.py
lm_mcp/auth/__init__.py
lm_mcp/auth/bearer.py
lm_mcp/auth/lmv1.py
lm_mcp/client/__init__.py
lm_mcp/client/api.py
lm_mcp/completions/__init__.py
lm_mcp/completions/handlers.py
lm_mcp/completions/registry.py
lm_mcp/prompts/__init__.py
lm_mcp/prompts/registry.py
lm_mcp/prompts/templates.py
lm_mcp/resources/__init__.py
lm_mcp/resources/enums.py
lm_mcp/resources/filters.py
lm_mcp/resources/registry.py
lm_mcp/resources/schemas.py
lm_mcp/tools/__init__.py
lm_mcp/tools/access_groups.py
lm_mcp/tools/alert_rules.py
lm_mcp/tools/alerts.py
lm_mcp/tools/api_tokens.py
lm_mcp/tools/audit.py
lm_mcp/tools/batchjobs.py
lm_mcp/tools/collectors.py
lm_mcp/tools/configsources.py
lm_mcp/tools/cost.py
lm_mcp/tools/dashboard_groups.py
lm_mcp/tools/dashboards.py
lm_mcp/tools/datasources.py
lm_mcp/tools/devices.py
lm_mcp/tools/escalations.py
lm_mcp/tools/eventsources.py
lm_mcp/tools/imports.py
lm_mcp/tools/ingestion.py
lm_mcp/tools/logsources.py
lm_mcp/tools/metrics.py
lm_mcp/tools/netscans.py
lm_mcp/tools/oids.py
lm_mcp/tools/ops.py
lm_mcp/tools/propertysources.py
lm_mcp/tools/reports.py
lm_mcp/tools/resources.py
lm_mcp/tools/sdts.py
lm_mcp/tools/services.py
lm_mcp/tools/session.py
lm_mcp/tools/topology.py
lm_mcp/tools/topologysources.py
lm_mcp/tools/users.py
lm_mcp/tools/websites.py
lm_mcp/transport/__init__.py
lm_mcp/transport/http.py
lm_mcp-1.1.0.dist-info/METADATA
lm_mcp-1.1.0.dist-info/WHEEL
lm_mcp-1.1.0.dist-info/entry_points.txt
lm_mcp-1.1.0.dist-info/licenses/LICENSE
lm_mcp-1.1.0.dist-info/RECORD
