Metadata-Version: 2.4
Name: lm-mcp
Version: 1.1.0
Summary: MCP server for LogicMonitor platform API integration
Project-URL: Homepage, https://github.com/ryanmat/mcp-server-logicmonitor
Project-URL: Repository, https://github.com/ryanmat/mcp-server-logicmonitor
Project-URL: Issues, https://github.com/ryanmat/mcp-server-logicmonitor/issues
Author-email: Ryan Matuszewski <ryan.matuszewski@logicmonitor.com>
License: MIT
License-File: LICENSE
Keywords: api,logicmonitor,mcp,model-context-protocol,monitoring
Classifier: Development Status :: 5 - Production/Stable
Classifier: Intended Audience :: Developers
Classifier: Intended Audience :: System Administrators
Classifier: License :: OSI Approved :: MIT License
Classifier: Operating System :: OS Independent
Classifier: Programming Language :: Python :: 3
Classifier: Programming Language :: Python :: 3.11
Classifier: Programming Language :: Python :: 3.12
Classifier: Programming Language :: Python :: 3.13
Classifier: Topic :: System :: Monitoring
Classifier: Topic :: System :: Systems Administration
Classifier: Typing :: Typed
Requires-Python: >=3.11
Requires-Dist: httpx>=0.27.0
Requires-Dist: mcp>=1.0.0
Requires-Dist: pydantic-settings>=2.0.0
Requires-Dist: pydantic>=2.0.0
Requires-Dist: python-dotenv>=1.0.0
Provides-Extra: http
Requires-Dist: starlette>=0.40.0; extra == 'http'
Requires-Dist: uvicorn[standard]>=0.30.0; extra == 'http'
